[
    {
        "nombre": "Juan",
        "apellido": "P\u00e9rez",
        "dni": "12345678A",
        "email": "juan.perez@example.com",
        "telefono": "+34912345678",
        "direccion": "Calle Falsa 123",
        "usuario": "juanperez",
        "contrasena": "password123"
    },
    {
        "nombre": "Ana",
        "apellido": "G\u00f3mez",
        "dni": "23456789B",
        "email": "ana.gomez@example.com",
        "telefono": "+34923456789",
        "direccion": "Avenida Real 456",
        "usuario": "anagomez",
        "contrasena": "password456"
    },
    {
        "nombre": "Carlos",
        "apellido": "Lopez",
        "dni": "34567890C",
        "email": "carlos.lopez@example.com",
        "telefono": "+34934567890",
        "direccion": "Plaza Mayor 789",
        "usuario": "carloslopez",
        "contrasena": "password789"
    },
    {
        "nombre": "Maria",
        "apellido": "Mart\u00ednez",
        "dni": "45678901D",
        "email": "maria.martinez@example.com",
        "telefono": "+34945678901",
        "direccion": "Calle del Sol 101",
        "usuario": "mariamartinez",
        "contrasena": "password101"
    },
    {
        "nombre": "Pedro",
        "apellido": "Fern\u00e1ndez",
        "dni": "56789012E",
        "email": "pedro.fernandez@example.com",
        "telefono": "+34956789012",
        "direccion": "Avenida del Mar 202",
        "usuario": "pedrofernandez",
        "contrasena": "password202"
    },
    {
        "nombre": "Laura",
        "apellido": "Hern\u00e1ndez",
        "dni": "67890123F",
        "email": "laura.hernandez@example.com",
        "telefono": "+34967890123",
        "direccion": "Calle de la Luna 303",
        "usuario": "laurahernandez",
        "contrasena": "password303"
    },
    {
        "nombre": "Jos\u00e9",
        "apellido": "Garc\u00eda",
        "dni": "78901234G",
        "email": "jose.garcia@example.com",
        "telefono": "+34978901234",
        "direccion": "Calle del R\u00edo 404",
        "usuario": "josegarcia",
        "contrasena": "password404"
    },
    {
        "nombre": "Isabel",
        "apellido": "Rodr\u00edguez",
        "dni": "89012345H",
        "email": "isabel.rodriguez@example.com",
        "telefono": "+34989012345",
        "direccion": "Calle de la Estrella 505",
        "usuario": "isabelrodriguez",
        "contrasena": "password505"
    },
    {
        "nombre": "Jorge",
        "apellido": "\u00c1lvarez",
        "dni": "90123456I",
        "email": "jorge.alvarez@example.com",
        "telefono": "+34990123456",
        "direccion": "Calle del Viento 606",
        "usuario": "jorgealvarez",
        "contrasena": "password606"
    },
    {
        "nombre": "Elena",
        "apellido": "P\u00e9rez",
        "dni": "01234567J",
        "email": "elena.perez@example.com",
        "telefono": "+34901234567",
        "direccion": "Calle del Bosque 707",
        "usuario": "elenaperez",
        "contrasena": "password707"
    },
    {
        "nombre": "pedrofernandez",
        "apellido": "pedrofernandez",
        "dni": "2222",
        "email": "22qq@qq",
        "telefono": "22w22",
        "direccion": "qq22",
        "usuario": "pedrofernandez1",
        "contrasena": "sa"
    }
]