[
    {
        "id": 1,
        "title": "Convocatoria de Investigación 2024",
        "description": "Convocatoria para proyectos de investigación en ciencias sociales.",
        "startDate": "2024-01-01",
        "endDate": "2024-06-30",
        "status": "Abierta",
        "registered": true
    },
    {
        "id": 2,
        "title": "Convocatoria de Innovación Educativa",
        "description": "Proyectos innovadores en el ámbito educativo.",
        "startDate": "2024-03-01",
        "endDate": "2024-09-30",
        "status": "Cerrada",
        "registered": true
    },
    {
        "id": 3,
        "title": "Convocatoria de Desarrollo Tecnológico",
        "description": "Desarrollo de nuevas tecnologías para el sector industrial.",
        "startDate": "2024-02-15",
        "endDate": "2024-08-15",
        "status": "Abierta",
        "registered": false
    }
]
